funmodels/__init__.py
funmodels/mivolo/__init__.py
funmodels/mivolo/predictor.py
funmodels/mivolo/structures.py
funmodels/mivolo/version.py
funmodels/mivolo/data/__init__.py
funmodels/mivolo/data/data_reader.py
funmodels/mivolo/data/misc.py
funmodels/mivolo/data/dataset/__init__.py
funmodels/mivolo/data/dataset/age_gender_dataset.py
funmodels/mivolo/data/dataset/age_gender_loader.py
funmodels/mivolo/data/dataset/classification_dataset.py
funmodels/mivolo/data/dataset/reader_age_gender.py
funmodels/mivolo/model/__init__.py
funmodels/mivolo/model/create_timm_model.py
funmodels/mivolo/model/cross_bottleneck_attn.py
funmodels/mivolo/model/mi_volo.py
funmodels/mivolo/model/mivolo_model.py
funmodels/mivolo/model/yolo_detector.py
funmodels_mivolo-0.0.2.dist-info/LICENSE
funmodels_mivolo-0.0.2.dist-info/METADATA
funmodels_mivolo-0.0.2.dist-info/WHEEL
funmodels_mivolo-0.0.2.dist-info/top_level.txt
funmodels_mivolo-0.0.2.dist-info/RECORD
